xlsx2csv_mergefill/__init__.py
xlsx2csv_mergefill/core.py
xlsx2csv_mergefill-1.0.2.dist-info/LICENSE
xlsx2csv_mergefill-1.0.2.dist-info/METADATA
xlsx2csv_mergefill-1.0.2.dist-info/WHEEL
xlsx2csv_mergefill-1.0.2.dist-info/top_level.txt
xlsx2csv_mergefill-1.0.2.dist-info/RECORD
