Metadata-Version: 2.1
Name: xlsx2csv-mergefill
Version: 1.0.2
Summary: Simple Excel to CSV converter with merged-cell propagation and cp932 encoding
Author: abachan
Author-email: aiba1114@cl.cilas.net
License: MIT
Project-URL: Homepage, https://github.com/your-username/xlsx2csv-mergefill
Project-URL: Repository, https://github.com/your-username/xlsx2csv-mergefill.git
Project-URL: Issues, https://github.com/your-username/xlsx2csv-mergefill/issues
Keywords: excel,csv,converter,merged-cells,cp932,shift-jis,japanese
Classifier: Development Status :: 5 - Production/Stable
Classifier: Intended Audience :: Developers
Classifier: License :: OSI Approved :: MIT License
Classifier: Programming Language :: Python :: 3
Classifier: Programming Language :: Python :: 3.9
Classifier: Programming Language :: Python :: 3.10
Classifier: Programming Language :: Python :: 3.11
Classifier: Programming Language :: Python :: 3.12
Classifier: Topic :: Office/Business :: Office Suites
Classifier: Topic :: Software Development :: Libraries :: Python Modules
Classifier: Topic :: Text Processing
Requires-Python: >=3.9
License-File: LICENSE
Requires-Dist: openpyxl>=3.1.0
Provides-Extra: dev
Requires-Dist: pytest>=7.0.0; extra == "dev"
Requires-Dist: pytest-cov>=4.0.0; extra == "dev"
